pipelinehub/__init__.py
pipelinehub/pipeline.py
pipelinehub/utils.py
pipelinehub-0.1.0.dist-info/LICENSE
pipelinehub-0.1.0.dist-info/METADATA
pipelinehub-0.1.0.dist-info/WHEEL
pipelinehub-0.1.0.dist-info/top_level.txt
pipelinehub-0.1.0.dist-info/RECORD
