Metadata-Version: 2.1
Name: pipelinehub
Version: 0.1.0
Summary: A flexible data pipeline library for custom data processing workflows
Home-page: https://github.com/rahulxj100/pipelinehub
Author: Rahul Paul
Author-email: Rahul Paul <paul.rahulxj100@gmail.com>
License: MIT
Project-URL: Homepage, https://github.com/rahulxj100/pipelinehub
Project-URL: Bug Reports, https://github.com/rahulxj100/pipelinehub/issues
Project-URL: Source, https://github.com/rahulxj100/pipelinehub
Keywords: pipeline,data,processing,workflow,etl
Classifier: Development Status :: 4 - Beta
Classifier: Intended Audience :: Developers
Classifier: License :: OSI Approved :: MIT License
Classifier: Programming Language :: Python :: 3
Classifier: Programming Language :: Python :: 3.7
Classifier: Programming Language :: Python :: 3.8
Classifier: Programming Language :: Python :: 3.9
Classifier: Programming Language :: Python :: 3.10
Classifier: Programming Language :: Python :: 3.11
Classifier: Programming Language :: Python :: 3.12
Classifier: Topic :: Software Development :: Libraries :: Python Modules
Classifier: Topic :: Scientific/Engineering :: Information Analysis
Requires-Python: >=3.7
License-File: LICENSE
Provides-Extra: dev
Requires-Dist: pytest>=6.0; extra == "dev"
Requires-Dist: black; extra == "dev"
Requires-Dist: flake8; extra == "dev"
Requires-Dist: mypy; extra == "dev"
